atproto_jetstream/__init__.py
atproto_jetstream/py.typed
atproto_jetstream-0.2.0.dist-info/licenses/LICENSE
atproto_jetstream-0.2.0.dist-info/METADATA
atproto_jetstream-0.2.0.dist-info/WHEEL
atproto_jetstream-0.2.0.dist-info/top_level.txt
atproto_jetstream-0.2.0.dist-info/RECORD
