Metadata-Version: 2.4
Name: atproto_jetstream
Version: 0.2.0
Summary: Receive Jetstream events from the AT Protocol
License-Expression: MIT
Project-URL: Repository, https://tangled.org/@nauta.one/atproto_jetstream
Project-URL: Issues, https://tangled.org/@nauta.one/atproto_jetstream/issues
Requires-Python: >=3.12
License-File: LICENSE
Requires-Dist: aiohttp>=3.13.0
Dynamic: license-file
